{
    "packages": [],
    "includes": {
        "include/all$33e88bc3ddaae5188a4162ddc085aa29df9ac186.json": {
            "sha1": "33e88bc3ddaae5188a4162ddc085aa29df9ac186"
        }
    },
    "metadata-url": "/p2/%package%.json",
    "available-packages": [
        "automattic/remote-data-blocks",
        "fairpm/fair-beacon",
        "fairpm/fair-plugin",
        "humanmade/ai",
        "jazzsequence/artists",
        "jazzsequence/releases",
        "jazzsequence/reviews",
        "markjaquith/gifdrop",
        "pantheon-systems/pantheon-content-publisher-wordpress"
    ]
}
