{
    "packages": [],
    "includes": {
        "include/all$0296ec7ffcbe05042f9227d282e3ae1eb4c45dde.json": {
            "sha1": "0296ec7ffcbe05042f9227d282e3ae1eb4c45dde"
        }
    },
    "metadata-url": "/p2/%package%.json",
    "available-packages": [
        "automattic/remote-data-blocks",
        "fairpm/fair-beacon",
        "fairpm/fair-plugin",
        "humanmade/ai",
        "jazzsequence/artists",
        "jazzsequence/releases",
        "jazzsequence/reviews",
        "markjaquith/gifdrop",
        "pantheon-systems/pantheon-content-publisher-wordpress"
    ]
}
